<?xml version="1.0" encoding="utf-8"?>
<savedqueries xmlns:xsi="http://www.w3.org/2001/XMLSchema-instance">
  <savedquery>
    <IsCustomizable>1</IsCustomizable>
    <CanBeDeleted>0</CanBeDeleted>
    <isquickfindquery>0</isquickfindquery>
    <isprivate>0</isprivate>
    <isdefault>1</isdefault>
    <savedqueryid>{b329294f-f09c-45ce-9bdf-e9a7c4c5dc61}</savedqueryid>
    <layoutxml>
      <grid name="cr468_dm_projectses" jump="cr468_projectname" select="1" icon="1" preview="1">
        <row name="cr468_dm_projects" id="cr468_dm_projectsid">
          <cell name="cr468_projectname" width="300" />
          <cell name="createdon" width="125" />
        </row>
      </grid>
    </layoutxml>
    <querytype>2</querytype>
    <fetchxml>
      <fetch version="1.0" mapping="logical">
        <entity name="cr468_dm_projects">
          <attribute name="cr468_dm_projectsid" />
          <attribute name="cr468_projectname" />
          <attribute name="createdon" />
          <order attribute="cr468_projectname" descending="false" />
          <filter type="and">
            <condition attribute="statecode" operator="eq" value="0" />
          </filter>
        </entity>
      </fetch>
    </fetchxml>
    <IntroducedVersion>1.0</IntroducedVersion>
    <LocalizedNames>
      <LocalizedName description="DM_Projects Associated View" languagecode="1033" />
    </LocalizedNames>
  </savedquery>
</savedqueries>